[
  {
    "model": "auth.user",
    "pk": 1,
    "fields": {
      "username": "alice@example.com",
      "password": "alice_password",
      "is_superuser": false,
      "is_staff": false,
      "is_active": true,
      "email": "alice@example.com"
    }
  },
  {
    "model": "auth.user",
    "pk": 2,
    "fields": {
      "username": "bob@example.com",
      "password": "bob_password",
      "is_superuser": false,
      "is_staff": false,
      "is_active": true,
      "email": "bob@example.com"
    }
  },
  {
    "model": "auth.user",
    "pk": 3,
    "fields": {
      "username": "brownie@example.com",
      "password": "brownie_password",
      "is_superuser": false,
      "is_staff": false,
      "is_active": true,
      "email": "brownie@example.com"
    }
  },
  {
    "model": "auth.user",
    "pk": 4,
    "fields": {
      "username": "admin@admin.com",
      "password": "password",
      "is_superuser": true,
      "is_staff": true,
      "is_active": true,
      "email": "admin@admin.com"
    }
  },
  {
    "model": "necysc_app.applicant",
    "pk": 1,
    "fields": {
      "user": 1,
      "created_at": "2024-10-26T08:00:00Z",
      "last_updated_at": "2024-10-26T08:00:00Z",
      "app_year": 2024,
      "app_status": "P",
      "health_record_status": "NC",
      "applicant_fname": "John",
      "applicant_lname": "Doe",
      "applicant_chinese_name": "",
      "applicant_email": "john.doe@email.com",
      "parent1_fname": "Jane",
      "parent1_lname": "Doe",
      "parent1_relationship": "M",
      "parent1_phone": "123-456-7890",
      "parent1_email": "jane.doe@email.com",
      "parent1_for_POD": true,
      "parent2_fname": "Tom",
      "parent2_lname": "Doe",
      "parent2_relationship": "F",
      "parent2_phone": "123-456-7891",
      "parent2_email": "tom.doe@email.com",
      "parent2_for_POD": false,
      "interest_in_POD_lead": false,
      "additional_emergency_contact_fname": "Sam",
      "additional_emergency_contact_lname": "Smith",
      "additional_emergency_contact_relationship": "Uncle",
      "additional_emergency_contact_phone": "321-654-0987",
      "street_address": "123 Elm Street",
      "city": "Anytown",
      "state": "CA",
      "zip_code": "90210",
      "applicant_bday": "2010-06-15",
      "applicant_sex": "M",
      "applicant_grade": 7,
      "applicant_shirt_size": "YM",
      "program": "O",
      "payment_received": false,
      "payment_total": "350.00",
      "payment_camp": "350.00",
      "payment_donation": "0.00",
      "payment_pod": "0.00",
      "allowed_pickup_persons": "Jane Doe, Tom Doe",
      "financial_aid_requested": false,
      "listing_on_weekbook": false,
      "camper_contact_email": "john.doe@camp.com",
      "interest_in_committee": false,
      "interest_in_wkbook_ads": false,
      "available_for_carpool": true,
      "referrals": "",
      "heard_from": "Online Search",
      "preferred_roommate": "",
      "health_form_a_received": true,
      "health_form_b_received": false,
      "medication_slip_received": false,
      "parent1_cori_status": "Pending",
      "parent1_sori_status": "Pending",
      "parent1_id_status": "Not Verified",
      "parent2_cori_status": "Pending",
      "parent2_sori_status": "Pending",
      "parent2_id_status": "Not Verified",
      "camper_cori_status": "Pending",
      "camper_sori_status": "Pending",
      "camper_id_status": "Not Verified",
      "camp_rule_agreement": true,
      "liability_agreement": true,
      "insurance_provider": "HealthFirst",
      "subscriber_name": "Jane Doe",
      "primary_physician_name": "Dr. Clark",
      "primary_physician_phone": "555-123-4567",
      "grant_hospital_permission": true,
      "grant_medical_treatment_permission": true,
      "grant_first_aid_permission": true,
      "grant_meds_permission": true,
      "grant_bug_spray_permission": true,
      "grant_skin_treatment_permission": true,
      "allergies": true,
      "allergies_description": "Peanuts",
      "initial_for_allergy_treatment": "JD",
      "epi_pen_prescribed": true,
      "social_emotional_concerns": "N/A",
      "wear_glasses": false,
      "wear_contacts": false,
      "wear_hearing_aids": false,
      "medication": true,
      "medication_description": "Antihistamine",
      "opt_out_activities": "",
      "medical_comments": "",
      "signature": "John Doe",
      "group_id": "1",
      "room_id": "A11",
      "internal_comments": ""
    }
  },
  {
    "model": "necysc_app.applicant",
    "pk": 2,
    "fields": {
      "user": 2,
      "created_at": "2024-10-25T12:00:00Z",
      "last_updated_at": "2024-10-25T12:00:00Z",
      "app_year": 2024,
      "app_status": "P",
      "health_record_status": "C",
      "applicant_fname": "Sophia",
      "applicant_lname": "Kim",
      "applicant_chinese_name": "",
      "applicant_email": "sophia.kim@email.com",
      "parent1_fname": "John",
      "parent1_lname": "Kim",
      "parent1_relationship": "F",
      "parent1_phone": "555-123-4567",
      "parent1_email": "john.kim@email.com",
      "parent1_for_POD": true,
      "parent2_fname": "Alice",
      "parent2_lname": "Kim",
      "parent2_relationship": "M",
      "parent2_phone": "555-987-6543",
      "parent2_email": "alice.kim@email.com",
      "parent2_for_POD": false,
      "interest_in_POD_lead": false,
      "additional_emergency_contact_fname": "Jake",
      "additional_emergency_contact_lname": "Kim",
      "additional_emergency_contact_relationship": "Uncle",
      "additional_emergency_contact_phone": "555-876-5432",
      "street_address": "123 Maple Street",
      "city": "Springfield",
      "state": "CA",
      "zip_code": "90210",
      "applicant_bday": "2010-06-15",
      "applicant_sex": "F",
      "applicant_grade": 7,
      "applicant_shirt_size": "M",
      "program": "S",
      "payment_received": true,
      "payment_total": "350.00",
      "payment_camp": "300.00",
      "payment_donation": "50.00",
      "payment_pod": "0.00",
      "allowed_pickup_persons": "John Kim, Alice Kim",
      "financial_aid_requested": false,
      "listing_on_weekbook": true,
      "camper_contact_email": "sophia.kim@camp.com",
      "interest_in_committee": false,
      "interest_in_wkbook_ads": true,
      "available_for_carpool": true,
      "referrals": "Friend",
      "heard_from": "Website",
      "preferred_roommate": "Emily Brown",
      "health_form_a_received": false,
      "health_form_b_received": true,
      "medication_slip_received": true,
      "parent1_cori_status": "Approved",
      "parent1_sori_status": "Approved",
      "parent1_id_status": "Verified",
      "parent2_cori_status": "Pending",
      "parent2_sori_status": "Pending",
      "parent2_id_status": "Verified",
      "camper_cori_status": "Approved",
      "camper_sori_status": "Approved",
      "camper_id_status": "Verified",
      "camp_rule_agreement": true,
      "liability_agreement": true,
      "insurance_provider": "Blue Cross",
      "subscriber_name": "John Kim",
      "primary_physician_name": "Dr. Smith",
      "primary_physician_phone": "555-222-3333",
      "grant_hospital_permission": true,
      "grant_medical_treatment_permission": true,
      "grant_first_aid_permission": true,
      "grant_meds_permission": true,
      "grant_bug_spray_permission": true,
      "grant_skin_treatment_permission": true,
      "allergies": true,
      "allergies_description": "Peanuts",
      "initial_for_allergy_treatment": "SK",
      "epi_pen_prescribed": true,
      "social_emotional_concerns": "Child does not like working with other people.",
      "wear_glasses": true,
      "wear_contacts": false,
      "wear_hearing_aids": false,
      "medication": true,
      "medication_description": "Antihistamines",
      "opt_out_activities": "",
      "medical_comments": "",
      "signature": "Sophia Kim",
      "group_id": "2",
      "room_id": "B12",
      "internal_comments": "No additional concerns."
    }
  },
  {
    "model": "necysc_app.applicant",
    "pk": 3,
    "fields": {
      "user": 2,
      "created_at": "2024-10-26T15:00:00Z",
      "last_updated_at": "2024-10-26T15:00:00Z",
      "app_year": 2024,
      "app_status": "A",
      "health_record_status": "P",
      "applicant_fname": "James",
      "applicant_lname": "Kim",
      "applicant_chinese_name": "",
      "applicant_email": "james.kim@email.com",
      "parent1_fname": "John",
      "parent1_lname": "Kim",
      "parent1_relationship": "F",
      "parent1_phone": "555-123-4567",
      "parent1_email": "john.kim@email.com",
      "parent1_for_POD": true,
      "parent2_fname": "Alice",
      "parent2_lname": "Kim",
      "parent2_relationship": "M",
      "parent2_phone": "555-987-6543",
      "parent2_email": "alice.kim@email.com",
      "parent2_for_POD": false,
      "interest_in_POD_lead": true,
      "additional_emergency_contact_fname": "Jake",
      "additional_emergency_contact_lname": "Kim",
      "additional_emergency_contact_relationship": "Uncle",
      "additional_emergency_contact_phone": "555-876-5432",
      "street_address": "123 Maple Street",
      "city": "Springfield",
      "state": "CA",
      "zip_code": "90210",
      "applicant_bday": "2011-03-20",
      "applicant_sex": "M",
      "applicant_grade": 6,
      "applicant_shirt_size": "YL",
      "program": "O",
      "payment_received": false,
      "payment_total": "250.00",
      "payment_camp": "250.00",
      "payment_donation": "0.00",
      "payment_pod": "0.00",
      "allowed_pickup_persons": "John Kim, Alice Kim",
      "financial_aid_requested": true,
      "listing_on_weekbook": false,
      "camper_contact_email": "james.kim@camp.com",
      "interest_in_committee": true,
      "interest_in_wkbook_ads": false,
      "available_for_carpool": true,
      "referrals": "School",
      "heard_from": "Flyer",
      "preferred_roommate": "",
      "health_form_a_received": true,
      "health_form_b_received": false,
      "medication_slip_received": false,
      "parent1_cori_status": "Approved",
      "parent1_sori_status": "Approved",
      "parent1_id_status": "Verified",
      "parent2_cori_status": "Pending",
      "parent2_sori_status": "Pending",
      "parent2_id_status": "Verified",
      "camper_cori_status": "Pending",
      "camper_sori_status": "Pending",
      "camper_id_status": "Not Verified",
      "camp_rule_agreement": true,
      "liability_agreement": true,
      "insurance_provider": "Cigna",
      "subscriber_name": "John Kim",
      "primary_physician_name": "Dr. Green",
      "primary_physician_phone": "555-234-5678",
      "grant_hospital_permission": true,
      "grant_medical_treatment_permission": true,
      "grant_first_aid_permission": true,
      "grant_meds_permission": true,
      "grant_bug_spray_permission": true,
      "grant_skin_treatment_permission": true,
      "allergies": false,
      "allergies_description": "",
      "initial_for_allergy_treatment": "",
      "epi_pen_prescribed": false,
      "social_emotional_concerns": "",
      "wear_glasses": true,
      "wear_contacts": false,
      "wear_hearing_aids": false,
      "medication": false,
      "medication_description": "",
      "opt_out_activities": "",
      "medical_comments": "N/A",
      "signature": "James Kim",
      "group_id": "3",
      "room_id": "C15",
      "internal_comments": "Shows interest in camp leadership roles."
    }
  },
  {
    "model": "necysc_app.applicant",
    "pk": 4,
    "fields": {
      "user": 3,
      "created_at": "2024-10-26T16:30:00Z",
      "last_updated_at": "2024-10-26T16:30:00Z",
      "app_year": 2024,
      "app_status": "R",
      "health_record_status": "NC",
      "applicant_fname": "Emily",
      "applicant_lname": "Brown",
      "applicant_chinese_name": "",
      "applicant_email": "emily.brown@email.com",
      "parent1_fname": "Michael",
      "parent1_lname": "Johnson",
      "parent1_relationship": "F",
      "parent1_phone": "555-567-1234",
      "parent1_email": "daniel.brown@email.com",
      "parent1_for_POD": false,
      "parent2_fname": "Emily",
      "parent2_lname": "Johnson",
      "parent2_relationship": "M",
      "parent2_phone": "555-567-5678",
      "parent2_email": "susan.brown@email.com",
      "parent2_for_POD": true,
      "interest_in_POD_lead": false,
      "additional_emergency_contact_fname": "Laura",
      "additional_emergency_contact_lname": "Brown",
      "additional_emergency_contact_relationship": "Grandmother",
      "additional_emergency_contact_phone": "555-765-4321",
      "street_address": "123 Cedar Lane",
      "city": "Newtown",
      "state": "FL",
      "zip_code": "33101",
      "applicant_bday": "2012-05-25",
      "applicant_sex": "F",
      "applicant_grade": 5,
      "applicant_shirt_size": "YS",
      "program": "D",
      "payment_received": false,
      "payment_total": "300.00",
      "payment_camp": "300.00",
      "payment_donation": "0.00",
      "payment_pod": "0.00",
      "allowed_pickup_persons": "Daniel Brown, Susan Brown",
      "financial_aid_requested": false,
      "listing_on_weekbook": true,
      "camper_contact_email": "emily.brown@camp.com",
      "interest_in_committee": false,
      "interest_in_wkbook_ads": true,
      "available_for_carpool": false,
      "referrals": "",
      "heard_from": "School Newsletter",
      "preferred_roommate": "James Smith",
      "health_form_a_received": false,
      "health_form_b_received": true,
      "medication_slip_received": true,
      "parent1_cori_status": "Pending",
      "parent1_sori_status": "Pending",
      "parent1_id_status": "Verified",
      "parent2_cori_status": "Approved",
      "parent2_sori_status": "Approved",
      "parent2_id_status": "Verified",
      "camper_cori_status": "Pending",
      "camper_sori_status": "Pending",
      "camper_id_status": "Not Verified",
      "camp_rule_agreement": true,
      "liability_agreement": true,
      "insurance_provider": "United Healthcare",
      "subscriber_name": "Susan Brown",
      "primary_physician_name": "Dr. White",
      "primary_physician_phone": "555-876-5432",
      "grant_hospital_permission": true,
      "grant_medical_treatment_permission": true,
      "grant_first_aid_permission": true,
      "grant_meds_permission": false,
      "grant_bug_spray_permission": true,
      "grant_skin_treatment_permission": true,
      "allergies": true,
      "allergies_description": "Tree Nuts",
      "initial_for_allergy_treatment": "EB",
      "epi_pen_prescribed": true,
      "social_emotional_concerns": "Shyness",
      "wear_glasses": false,
      "wear_contacts": false,
      "wear_hearing_aids": false,
      "medication": true,
      "medication_description": "Antihistamine",
      "opt_out_activities": "",
      "medical_comments": "Takes antihistamine for tree nut allergies.",
      "signature": "Emily Brown",
      "group_id": "4",
      "room_id": "D18",
      "internal_comments": "Requires special attention due to allergies."
    }
  }
]
